altb/__init__.py
altb/common.py
altb/config.py
altb/constants.py
altb/main.py
altb/options.py
altb/track.py
altb-0.3.1.dist-info/entry_points.txt
altb-0.3.1.dist-info/WHEEL
altb-0.3.1.dist-info/METADATA
altb-0.3.1.dist-info/RECORD
