Metadata-Version: 2.1
Name: altb
Version: 0.3.1
Summary: Cli tool for tracking over binaries and easily swapping between them
Home-page: https://github.com/IamShobe/altb
License: MIT
Author: Elran Shefer
Author-email: elran777@gmail.com
Requires-Python: >=3.7,<4.0
Classifier: License :: OSI Approved :: MIT License
Classifier: Programming Language :: Python :: 3
Classifier: Programming Language :: Python :: 3 :: Only
Classifier: Programming Language :: Python :: 3.10
Classifier: Programming Language :: Python :: 3.7
Classifier: Programming Language :: Python :: 3.8
Classifier: Programming Language :: Python :: 3.9
Classifier: Topic :: Utilities
Requires-Dist: PyYAML (>=6.0,<7.0)
Requires-Dist: blessed (>=1.19.0,<2.0.0)
Requires-Dist: getch (>=1.0,<2.0)
Requires-Dist: natsort (>=8.0.1,<9.0.0)
Requires-Dist: pydantic (>=1.8.2,<2.0.0)
Requires-Dist: rich (>=10.15.2,<11.0.0)
Requires-Dist: typer (>=0.4.0,<0.5.0)
